__init__.py
oogeo/__init__.py
oogeo/functions/__init__.py
oogeo/functions/constants.py
oogeo/functions/conversions.py
oogeo/functions/database.py
oogeo/objects/__init__.py
oogeo/objects/cursor.py
oogeo/objects/geometrybase.py
oogeo/objects/layer.py
oogeo/objects/line.py
oogeo/objects/multipointbase.py
oogeo/objects/point.py
oogeo/objects/polygon.py
oogeo/objects/selectionset.py
oogeo/objects/table.py
oogeo/objects/workspace.py
oogeo/unittests/__init__.py
oogeo/unittests/databasetest.py
oogeo/unittests/fauxprocess.py
oogeo/unittests/layertest.py
oogeo/unittests/linetest.py
oogeo/unittests/pointtest.py
oogeo/unittests/polygontest.py
oogeo/unittests/run.py
oogeo/unittests/tabletest.py
oogeo/unittests/utilities.py
oogeo/unittests/utilstest.py
oogeo/unittests/workspacetest.py
oogeo-0.0.11.dist-info/LICENSE.txt
oogeo-0.0.11.dist-info/METADATA
oogeo-0.0.11.dist-info/WHEEL
oogeo-0.0.11.dist-info/top_level.txt
oogeo-0.0.11.dist-info/RECORD
