Metadata-Version: 2.1
Name: oogeo
Version: 0.0.11
Summary: An open source library for processing geospatial data using Python and PostGIS.
Author-email: Brian Lott <briguy360@gmail.com>
Project-URL: Homepage, https://github.com/bmlott27/oogeo
Project-URL: Bug Tracker, https://github.com/bmlott27/oogeo/issues
Keywords: GIS,PostGIS,Geoprocessing,Geodatabase
Classifier: Programming Language :: Python :: 3
Classifier: License :: OSI Approved :: MIT License
Classifier: Operating System :: OS Independent
Requires-Python: >=3.7
License-File: LICENSE.txt
Requires-Dist: matplotlib (==3.5.3)
Requires-Dist: Shapely (>=1.3.0)
Requires-Dist: GeoAlchemy2 (==0.12.3)
Requires-Dist: psycopg2 (==2.9.3)
Requires-Dist: numpy (==1.22.4)
Requires-Dist: SQLAlchemy (==1.4.40)
Requires-Dist: Pint (==0.19.2)
Requires-Dist: pyproj (==3.3.1)
Requires-Dist: more-itertools (==8.14.0)
